MANIFEST.in
README.txt
setup.py
SSHer.egg-info/PKG-INFO
SSHer.egg-info/SOURCES.txt
SSHer.egg-info/dependency_links.txt
SSHer.egg-info/requires.txt
SSHer.egg-info/top_level.txt
ssher/Config.py
ssher/Server.py
ssher/__init__.py
ssher/create_bin.py
ssher/ssher.py