Metadata-Version: 1.0
Name: SSHer
Version: 1.0.2
Summary: Multi ssh connection launcher
Home-page: UNKNOWN
Author: Guido Accardo
Author-email: gaccardo@gmail.com
License: UNKNOWN
Platform: UNKNOWN
